<?xml version="1.0" encoding="ISO-8859-1"?>
<PROPERTIES>
<!-- Aba: Representa nome da Aba em que o componente está presente. Valor: String. -->
<PROPERTY KEY="Aba">05-Eventos</PROPERTY>
<!-- Altura: Valor numérico que representa a altura de um componente ou formulário -->
<PROPERTY KEY="Altura">35</PROPERTY>
<PROPERTY KEY="AoClicar"></PROPERTY>
<PROPERTY KEY="AoModificar">[12]
Entrada=Nome Fluxo={MakerLookup1}
Nome=Integracao - Configuracoes - Exibir Parametros do Fluxo

</PROPERTY>
<!-- ApenasLeitura: Valor lógico que informa se o componente é apenas para leitura -->
<PROPERTY KEY="ApenasLeitura">False</PROPERTY>
<!-- Atributos: Informa os atributos de um componente. Valor: números separados por ";". -->
<PROPERTY KEY="Atributos"></PROPERTY>
<PROPERTY KEY="BuscaIncremental">False</PROPERTY>
<!-- Campo: Informa o valor do campo da consulta que o componente está associado. Valor: string. -->
<PROPERTY KEY="Campo"></PROPERTY>
<!-- CampoChave: Informa o campo chave do componente. Valor: string. -->
<PROPERTY KEY="CampoChave">REG_NOME</PROPERTY>
<!-- CampoLista: Informa o campo de exibição do componente. Valor: string. -->
<PROPERTY KEY="CampoLista">REG_NOME</PROPERTY>
<!-- ChamaSubForm: Informa se o componente deve chamar o subformulário definido na propriedade Formulário. Valor: true|false. -->
<PROPERTY KEY="ChamaSubForm">True</PROPERTY>
<PROPERTY KEY="ClasseCSS"></PROPERTY>
<!-- Codigo: Código do componente. Valor: inteiro. -->
<PROPERTY KEY="Codigo">1049201</PROPERTY>
<!-- CodigoForm: Código do formulário: Valor: inteiro. -->
<PROPERTY KEY="CodigoForm">0</PROPERTY>
<PROPERTY KEY="Container"></PROPERTY>
<!-- Cor: Valor númerico que representa uma cor. Utiliza o padrão Delphi. Valor: inteiro. -->
<PROPERTY KEY="Cor">-16777211</PROPERTY>
<!-- Descricao: Informa a descrição do campo. Valor: string. -->
<PROPERTY KEY="Descricao"></PROPERTY>
<!-- Dica: Texto de ajuda para o componente. Valor: string. -->
<PROPERTY KEY="Dica"></PROPERTY>
<!-- Estilo: Informa o estilo do lookup (Como, Edit e Memo). Valor: 0, 1 ou 2. -->
<PROPERTY KEY="Estilo">0</PROPERTY>
<PROPERTY KEY="EstiloCss"></PROPERTY>
<!-- Fonte: Representa uma fonte do sistema. Valor: Nome da Fonte, tamanho, propriedades, cor -->
<PROPERTY KEY="Fonte">MS Sans Serif,8,0000,clWindowText</PROPERTY>
<!-- FonteDeDados:  -->
<PROPERTY KEY="FonteDeDados"></PROPERTY>
<PROPERTY KEY="FonteDescricao"></PROPERTY>
<!-- Habilitado:  -->
<PROPERTY KEY="Habilitado">True</PROPERTY>
<PROPERTY KEY="LabelPosition">0</PROPERTY>
<PROPERTY KEY="LarguraExibicao">0</PROPERTY>
<!-- Mascara:  -->
<PROPERTY KEY="Mascara"></PROPERTY>
<!-- Nome:  -->
<PROPERTY KEY="Nome">MakerLookup1</PROPERTY>
<PROPERTY KEY="NomeClasseCss"></PROPERTY>
<!-- Ordem:  -->
<PROPERTY KEY="Ordem">9</PROPERTY>
<!-- Paginacao:  -->
<PROPERTY KEY="Paginacao">0</PROPERTY>
<PROPERTY KEY="Placeholder"></PROPERTY>
<!-- PosicaoX:  -->
<PROPERTY KEY="PosicaoX">13</PROPERTY>
<!-- PosicaoY:  -->
<PROPERTY KEY="PosicaoY">317</PROPERTY>
<!-- SQL:  -->
<PROPERTY KEY="SQL">Select
  FR_REGRAS.REG_NOME
From
  FR_REGRAS
Where (
  (FR_REGRAS.REG_NOME Not Like '%MKR_%') And
  (FR_REGRAS.REG_NOME Not Like '%TPT_%'))
/*WHERE_ADD*/
/*ORDER_NEW*/
</PROPERTY>
<!-- Tabulacao:  -->
<PROPERTY KEY="Tabulacao">3</PROPERTY>
<!-- Tabular:  -->
<PROPERTY KEY="Tabular">True</PROPERTY>
<!-- Tamanho: Valor numérico que representa a largura de um componente -->
<PROPERTY KEY="Tamanho">338</PROPERTY>
<!-- Tipo:  -->
<PROPERTY KEY="Tipo"></PROPERTY>
<PROPERTY KEY="TipoFiltroInicial">3</PROPERTY>
<PROPERTY KEY="ValorInicial"></PROPERTY>
<!-- Visivel:  -->
<PROPERTY KEY="Visivel">True</PROPERTY>
</PROPERTIES>